cocoindex_mcp/__init__.py
cocoindex_mcp/__main__.py
cocoindex_mcp/cli.py
cocoindex_mcp/config.py
cocoindex_mcp/db.py
cocoindex_mcp/runtime.py
cocoindex_mcp/search.py
cocoindex_mcp-0.0.2.dist-info/WHEEL
cocoindex_mcp-0.0.2.dist-info/entry_points.txt
cocoindex_mcp-0.0.2.dist-info/METADATA
cocoindex_mcp-0.0.2.dist-info/RECORD
