Metadata-Version: 2.3
Name: cocoindex-mcp
Version: 0.0.2
Summary: MCP server for querying cocoindex code embeddings database
Author: Yasser Alattas
Author-email: Yasser Alattas <y.alattas@gmail.com>
Classifier: Programming Language :: Python :: 3
Classifier: Development Status :: 3 - Alpha
Classifier: Intended Audience :: Developers
Classifier: Topic :: Scientific/Engineering :: Artificial Intelligence
Requires-Dist: httpx>=0.28.1
Requires-Dist: mcp>=1.20.0
Requires-Dist: cocoindex
Requires-Dist: cocoindex[embeddings]
Requires-Dist: psycopg[binary,pool]
Requires-Dist: pgvector
Requires-Dist: numpy
Requires-Dist: python-dotenv
Requires-Python: >=3.11
Project-URL: homepage, https://github.com/yalattas/cocoindex-mcp
Project-URL: issues, https://github.com/yalattas/cocoindex-mcp/issues
Project-URL: repository, https://github.com/yalattas/cocoindex-mcp
